pytax/__init__.py
pytax/cli.py
pytax/pytax.py
pytax-0.2.0.dist-info/DESCRIPTION.rst
pytax-0.2.0.dist-info/METADATA
pytax-0.2.0.dist-info/RECORD
pytax-0.2.0.dist-info/WHEEL
pytax-0.2.0.dist-info/entry_points.txt
pytax-0.2.0.dist-info/metadata.json
pytax-0.2.0.dist-info/top_level.txt
