Metadata-Version: 2.0
Name: pytax
Version: 0.2.0
Summary: Python package to calculate price with TAX
Home-page: https://github.com/jacruzsdev/pytax
Author: Jesus Andres Cruz Sanabria
Author-email: j.cruz@ieee.org
License: MIT license
Keywords: pytax
Platform: UNKNOWN
Classifier: Development Status :: 2 - Pre-Alpha
Classifier: Intended Audience :: Developers
Classifier: License :: OSI Approved :: MIT License
Classifier: Natural Language :: English
Classifier: Programming Language :: Python :: 2
Classifier: Programming Language :: Python :: 2.7
Classifier: Programming Language :: Python :: 3
Classifier: Programming Language :: Python :: 3.4
Classifier: Programming Language :: Python :: 3.5
Classifier: Programming Language :: Python :: 3.6
Requires-Dist: Click (>=6.0)
